.coveragerc
.flake8
.gitignore
.isort.cfg
.pre-commit-config.yaml
.readthedocs.yml
AUTHORS.md
CHANGELOG.md
LICENSE.txt
MANIFEST.in
README.md
favicon.ico
pyproject.toml
setup.cfg
setup.py
tox.ini
src/circuitsascode/__init__.py
src/circuitsascode/utilities.py
src/circuitsascode.egg-info/PKG-INFO
src/circuitsascode.egg-info/SOURCES.txt
src/circuitsascode.egg-info/dependency_links.txt
src/circuitsascode.egg-info/not-zip-safe
src/circuitsascode.egg-info/requires.txt
src/circuitsascode.egg-info/top_level.txt
src/circuitsascode/dataconv/__init__.py
src/circuitsascode/dataconv/dac.py
src/circuitsascode/displays/__init__.py
src/circuitsascode/displays/vga.py
src/circuitsascode/fpgas/__init__.py
src/circuitsascode/interfaces/__init__.py
src/circuitsascode/interfaces/pmod.py
src/circuitsascode/linear/__init__.py
src/circuitsascode/mcus/__init__.py
src/circuitsascode/memories/__init__.py
src/circuitsascode/modules/__init__.py
src/circuitsascode/sensors/__init__.py
src/circuitsascode/simple/__init__.py
src/circuitsascode/simple/v_div.py
src/circuitsascode/vregs/__init__.py
src/circuitsascode/vregs/linear.py