Metadata-Version: 2.1
Name: circuitsascode
Version: 0.0.2
Summary: A collection of SKiDL modules for common electronic circuits.
Home-page: https://github.com/devbisme/circuitsascode
Author: Dave Vandenbout
Author-email: devb@xess.com
License: MIT
Project-URL: Twitter, https://twitter.com/circuitsascode
Project-URL: Tracker, https://github.com/devbisme/circuitsascode/issues
Project-URL: Changelog, https://github.com/devbisme/circuitsascode/latest/CHANGELOG.html
Project-URL: Source, https://github.com/devbisme/circuitsascode
Project-URL: Documentation, https://devbisme.github.io/circuitsascode
Keywords: skidl kicad electronic circuit schematics
Platform: UNKNOWN
Classifier: Development Status :: 3 - Alpha
Classifier: Intended Audience :: Manufacturing
Classifier: License :: OSI Approved :: MIT License
Classifier: Natural Language :: English
Classifier: Operating System :: OS Independent
Classifier: Programming Language :: Python :: 2.7
Classifier: Programming Language :: Python :: 3
Classifier: Programming Language :: Python :: Implementation :: CPython
Classifier: Topic :: Scientific/Engineering :: Electronic Design Automation (EDA)
License-File: LICENSE.txt
License-File: AUTHORS.md
